flakewall/__init__.py
flakewall/cli.py
flakewall/config.py
flakewall/gh.py
flakewall/junit.py
flakewall/junit_writer.py
flakewall/owners.py
flakewall/quarantine.py
flakewall/runner.py
flakewall-0.2.0.dist-info/licenses/LICENSE
flakewall-0.2.0.dist-info/METADATA
flakewall-0.2.0.dist-info/WHEEL
flakewall-0.2.0.dist-info/entry_points.txt
flakewall-0.2.0.dist-info/top_level.txt
flakewall-0.2.0.dist-info/RECORD
