Metadata-Version: 2.4
Name: flakewall
Version: 0.2.0
Summary: Local CI guard for flaky tests: parse JUnit XML, retry, and auto-quarantine
Author: Flakewall
License: MIT
Project-URL: Homepage, https://github.com/Cicatriiz/flakewall
Project-URL: Repository, https://github.com/Cicatriiz/flakewall
Project-URL: Issues, https://github.com/Cicatriiz/flakewall/issues
Classifier: License :: OSI Approved :: MIT License
Classifier: Programming Language :: Python :: 3
Classifier: Programming Language :: Python :: 3 :: Only
Classifier: Programming Language :: Python :: 3.9
Classifier: Programming Language :: Python :: 3.10
Classifier: Programming Language :: Python :: 3.11
Classifier: Programming Language :: Python :: 3.12
Classifier: Environment :: Console
Classifier: Intended Audience :: Developers
Classifier: Topic :: Software Development :: Testing
Requires-Python: >=3.9
License-File: LICENSE
Requires-Dist: typer>=0.12
Requires-Dist: PyYAML>=6.0
Provides-Extra: dev
Requires-Dist: pytest>=7.0; extra == "dev"
Requires-Dist: tox>=4.0; extra == "dev"
Requires-Dist: build>=1.2; extra == "dev"
Requires-Dist: twine>=5.0; extra == "dev"
Requires-Dist: black>=24.0; extra == "dev"
Dynamic: license-file
